rsa_so/__init__.py
rsa_so/bin/rsa_darwin_arm64.h
rsa_so/bin/rsa_darwin_arm64.so
rsa_so/bin/rsa_darwin_x86_64.h
rsa_so/bin/rsa_darwin_x86_64.so
rsa_so/bin/rsa_linux_x86_64.h
rsa_so/bin/rsa_linux_x86_64.so
rsa_so/sign.py
rsa_so-0.1.3.dist-info/METADATA
rsa_so-0.1.3.dist-info/WHEEL
rsa_so-0.1.3.dist-info/RECORD
